kongctl/__init__.py
kongctl/__main__.py
kongctl/client.py
kongctl/json_formatter.py
kongctl/logger.py
kongctl/resource_error.py
kongctl/resources.py
kongctl/yaml_formatter.py
kongctl-0.3.8.dist-info/LICENSE
kongctl-0.3.8.dist-info/METADATA
kongctl-0.3.8.dist-info/WHEEL
kongctl-0.3.8.dist-info/entry_points.txt
kongctl-0.3.8.dist-info/top_level.txt
kongctl-0.3.8.dist-info/RECORD
