Metadata-Version: 2.1
Name: kongctl
Version: 0.3.8
Summary: kongctl - a CLI for kong admin interface.
Home-page: https://github.com/kepkin/kongctl
Author: Alexander Nevskiy
Author-email: kepkin@gmail.com
License: BSD
Download-URL: https://github.com/kepkin/kongctl
Platform: UNKNOWN
Classifier: Development Status :: 3 - Alpha
Classifier: Programming Language :: Python
Classifier: Programming Language :: Python :: 3
Classifier: Programming Language :: Python :: 3.1
Classifier: Programming Language :: Python :: 3.2
Classifier: Programming Language :: Python :: 3.3
Classifier: Programming Language :: Python :: 3.4
Classifier: Programming Language :: Python :: 3.5
Classifier: Programming Language :: Python :: 3.6
Classifier: Environment :: Console
Classifier: Intended Audience :: Developers
Classifier: Intended Audience :: System Administrators
Classifier: License :: OSI Approved :: BSD License
Classifier: Topic :: Internet :: WWW/HTTP
Classifier: Topic :: Software Development
Classifier: Topic :: System :: Networking
Classifier: Topic :: Terminals
Classifier: Topic :: Text Processing
Classifier: Topic :: Utilities
Requires-Dist: requests (>=2.21.0)
Requires-Dist: termcolor (==1.1.0)
Requires-Dist: PyYAML (>=5.1.1)
